transgptex/__init__.py
transgptex/command_line.py
transgptex/config.py
transgptex/download_paper.py
transgptex/file_selector.py
transgptex/latex_spilter.py
transgptex/llm_api_async.py
transgptex/preprocess_tex.py
transgptex/translate_tex.py
transgptex-0.1.2.dist-info/LICENSE
transgptex-0.1.2.dist-info/METADATA
transgptex-0.1.2.dist-info/WHEEL
transgptex-0.1.2.dist-info/entry_points.txt
transgptex-0.1.2.dist-info/top_level.txt
transgptex-0.1.2.dist-info/RECORD
