Metadata-Version: 2.1
Name: transgptex
Version: 0.1.2
Summary: Translate Latex articles through LLM and compile them into PDF
Home-page: https://github.com/LiSheng2001/TransGPTex
Author: TransGPTex Developers
Author-email: lisheng@nuaa.edu.cn
License: MIT
Platform: UNKNOWN
Classifier: Programming Language :: Python :: 3
Classifier: License :: OSI Approved :: MIT License
Classifier: Operating System :: OS Independent
License-File: LICENSE
Requires-Dist: openai
Requires-Dist: arxiv
Requires-Dist: toml ; python_version < "3.11"
